AUTHORS
LICENSE
MANIFEST.in
README.rst
setup.py
django_nimda.egg-info/PKG-INFO
django_nimda.egg-info/SOURCES.txt
django_nimda.egg-info/dependency_links.txt
django_nimda.egg-info/not-zip-safe
django_nimda.egg-info/pbr.json
django_nimda.egg-info/requires.txt
django_nimda.egg-info/top_level.txt
nimda/__init__.py
nimda/static/admin/css/base.css
nimda/static/admin/css/base.css.map
nimda/static/admin/css/changelists.css
nimda/static/admin/css/changelists.css.map
nimda/static/admin/css/dashboard.css
nimda/static/admin/css/dashboard.css.map
nimda/static/admin/css/forms.css
nimda/static/admin/css/forms.css.map
nimda/static/admin/css/ie.css
nimda/static/admin/css/ie.css.map
nimda/static/admin/css/login.css
nimda/static/admin/css/login.css.map
nimda/static/admin/css/rtl.css
nimda/static/admin/css/rtl.css.map
nimda/static/admin/css/widgets.css
nimda/static/admin/css/widgets.css.map
nimda/static/admin/img/changelist-bg.gif
nimda/static/admin/img/changelist-bg_rtl.gif
nimda/static/admin/img/default-bg-reverse.gif
nimda/static/admin/img/default-bg.gif
nimda/static/admin/img/deleted-overlay.gif
nimda/static/admin/img/icon-no.gif
nimda/static/admin/img/icon-unknown.gif
nimda/static/admin/img/icon-yes.gif
nimda/static/admin/img/icon_addlink.gif
nimda/static/admin/img/icon_alert.gif
nimda/static/admin/img/icon_calendar.gif
nimda/static/admin/img/icon_changelink.gif
nimda/static/admin/img/icon_clock.gif
nimda/static/admin/img/icon_deletelink.gif
nimda/static/admin/img/icon_error.gif
nimda/static/admin/img/icon_searchbox.png
nimda/static/admin/img/icon_success.gif
nimda/static/admin/img/inline-delete-8bit.png
nimda/static/admin/img/inline-delete.png
nimda/static/admin/img/inline-restore-8bit.png
nimda/static/admin/img/inline-restore.png
nimda/static/admin/img/inline-splitter-bg.gif
nimda/static/admin/img/nav-bg-grabber.gif
nimda/static/admin/img/nav-bg-reverse.gif
nimda/static/admin/img/nav-bg-selected.gif
nimda/static/admin/img/nav-bg.gif
nimda/static/admin/img/selector-icons.gif
nimda/static/admin/img/selector-search.gif
nimda/static/admin/img/sorting-icons.gif
nimda/static/admin/img/tooltag-add.png
nimda/static/admin/img/tooltag-arrowright.png
nimda/static/admin/img/gis/move_vertex_off.png
