Metadata-Version: 1.1
Name: django-nimda
Version: 0.0.1
Summary: A light weight attempt at spicing up the django admin
Home-page: http://github.com/aino/django-nimda
Author: AIno
Author-email: hello@aino.com
License: ICS
Platform: UNKNOWN
Classifier: Development Status :: 3 - Alpha
Classifier: Environment :: Web Environment
Classifier: Intended Audience :: Developers
Classifier: License :: OSI Approved :: ISC License (ISCL)
Classifier: Operating System :: OS Independent
Classifier: Programming Language :: Python
Classifier: Programming Language :: Python :: 2.7
Classifier: Programming Language :: Python :: 3.4
Classifier: Framework :: Django
